wecomUtils/__init__.py
wecomUtils/db_manager.py
wecomUtils/fc_service.py
wecomUtils/storage.py
wecomutils-0.1.1.dist-info/licenses/LICENSE
wecomutils-0.1.1.dist-info/METADATA
wecomutils-0.1.1.dist-info/WHEEL
wecomutils-0.1.1.dist-info/top_level.txt
wecomutils-0.1.1.dist-info/RECORD
